netbox_freeipa/__init__.py
netbox_freeipa/admin.py
netbox_freeipa/filtersets.py
netbox_freeipa/forms.py
netbox_freeipa/freeipa_client.py
netbox_freeipa/jobs.py
netbox_freeipa/models.py
netbox_freeipa/navigation.py
netbox_freeipa/tables.py
netbox_freeipa/urls.py
netbox_freeipa/views.py
netbox_freeipa/api/__init__.py
netbox_freeipa/api/serializers.py
netbox_freeipa/api/urls.py
netbox_freeipa/api/views.py
netbox_freeipa/migrations/0001_initial.py
netbox_freeipa/migrations/0002_fix_fields.py
netbox_freeipa/migrations/0003_dns_models_and_update_host.py
netbox_freeipa/migrations/__init__.py
netbox_freeipa/templates/netbox_freeipa/freeipadnsrecord.html
netbox_freeipa/templates/netbox_freeipa/freeipadnsrecord_edit.html
netbox_freeipa/templates/netbox_freeipa/freeipadnsrecord_list.html
netbox_freeipa/templates/netbox_freeipa/freeipadnszone.html
netbox_freeipa/templates/netbox_freeipa/freeipadnszone_edit.html
netbox_freeipa/templates/netbox_freeipa/freeipadnszone_list.html
netbox_freeipa/templates/netbox_freeipa/freeipahost.html
netbox_freeipa/templates/netbox_freeipa/freeipahost_edit.html
netbox_freeipa/templates/netbox_freeipa/freeipahost_list.html
netbox_freeipa/templates/netbox_freeipa/freeipahost_sync.html
netbox_freeipa-0.3.0.dist-info/licenses/LICENSE
netbox_freeipa-0.3.0.dist-info/METADATA
netbox_freeipa-0.3.0.dist-info/WHEEL
netbox_freeipa-0.3.0.dist-info/top_level.txt
netbox_freeipa-0.3.0.dist-info/RECORD
