Metadata-Version: 2.4
Name: netbox-freeipa
Version: 0.3.0
Summary: NetBox plugin for FreeIPA integration - manage hosts, DNS zones and records
Author-email: Maksym Hrytsaienko <hrytsaienko.my@gmail.com>
License: Apache-2.0
Project-URL: Homepage, https://github.com/neverlless/netbox-freeipa
Project-URL: Documentation, https://github.com/neverlless/netbox-freeipa/blob/main/README.md
Project-URL: Repository, https://github.com/neverlless/netbox-freeipa
Project-URL: Bug Tracker, https://github.com/neverlless/netbox-freeipa/issues
Keywords: netbox,netbox-plugin,freeipa,identity-management
Classifier: Development Status :: 3 - Alpha
Classifier: Framework :: Django
Classifier: Intended Audience :: Developers
Classifier: Intended Audience :: System Administrators
Classifier: License :: OSI Approved :: Apache Software License
Classifier: Natural Language :: English
Classifier: Operating System :: OS Independent
Classifier: Programming Language :: Python :: 3
Classifier: Programming Language :: Python :: 3.10
Classifier: Programming Language :: Python :: 3.11
Classifier: Programming Language :: Python :: 3.12
Classifier: Topic :: System :: Systems Administration
Requires-Python: >=3.10
License-File: LICENSE
Requires-Dist: python-freeipa>=1.0.6
Dynamic: license-file
